[
   {
      "model":"products.variants",
      "pk":58,
      "fields":{
         "title":"Hudi",
         "product":125,
         "color":null,
         "size":3,
         "image_id":260,
         "quantity":35,
         "price":"35.00",
         "status":"True"
      }
   },
   {
      "model":"products.variants",
      "pk":59,
      "fields":{
         "title":"Men T-Shirts",
         "product":122,
         "color":null,
         "size":null,
         "image_id":0,
         "quantity":25,
         "price":"53.99",
         "status":"True"
      }
   },
   {
      "model":"products.variants",
      "pk":61,
      "fields":{
         "title":"Hudi Boys",
         "product":127,
         "color":5,
         "size":null,
         "image_id":267,
         "quantity":33,
         "price":"35.99",
         "status":"True"
      }
   },
   {
      "model":"products.variants",
      "pk":64,
      "fields":{
         "title":"Boys Hudi",
         "product":125,
         "color":null,
         "size":2,
         "image_id":263,
         "quantity":32,
         "price":"32.00",
         "status":"True"
      }
   },
   {
      "model":"products.variants",
      "pk":67,
      "fields":{
         "title":"Boys Shirts",
         "product":62,
         "color":null,
         "size":null,
         "image_id":0,
         "quantity":25,
         "price":"12.99",
         "status":"True"
      }
   },
   {
      "model":"products.variants",
      "pk":68,
      "fields":{
         "title":"Long body styling Hudi",
         "product":3,
         "color":null,
         "size":null,
         "image_id":0,
         "quantity":25,
         "price":"59.99",
         "status":"True"
      }
   },
   {
      "model":"products.variants",
      "pk":69,
      "fields":{
         "title":"Girls fitted trousers Black",
         "product":49,
         "color":34,
         "size":null,
         "image_id":416,
         "quantity":45,
         "price":"19.99",
         "status":"True"
      }
   },
   {
      "model":"products.variants",
      "pk":70,
      "fields":{
         "title":"Girls Dresses",
         "product":31,
         "color":null,
         "size":null,
         "image_id":0,
         "quantity":25,
         "price":"53.99",
         "status":"True"
      }
   },
   {
      "model":"products.variants",
      "pk":71,
      "fields":{
         "title":"Ladies Dresses",
         "product":94,
         "color":null,
         "size":null,
         "image_id":0,
         "quantity":20,
         "price":"53.99",
         "status":"True"
      }
   },
   {
      "model":"products.variants",
      "pk":72,
      "fields":{
         "title":"Ladies Shirts",
         "product":82,
         "color":null,
         "size":null,
         "image_id":0,
         "quantity":25,
         "price":"33.99",
         "status":"True"
      }
   },
   {
      "model":"products.variants",
      "pk":73,
      "fields":{
         "title":"Boys Hudi",
         "product":57,
         "color":null,
         "size":null,
         "image_id":0,
         "quantity":25,
         "price":"25.99",
         "status":"True"
      }
   },
   {
      "model":"products.variants",
      "pk":75,
      "fields":{
         "title":"Ladies Skirt and Shirt",
         "product":19,
         "color":null,
         "size":null,
         "image_id":0,
         "quantity":25,
         "price":"45.99",
         "status":"True"
      }
   },
   {
      "model":"products.variants",
      "pk":76,
      "fields":{
         "title":"Red Half Sleeves Sweater",
         "product":25,
         "color":5,
         "size":null,
         "image_id":369,
         "quantity":25,
         "price":"19.99",
         "status":"True"
      }
   },
   {
      "model":"products.variants",
      "pk":77,
      "fields":{
         "title":"Ladies Dresses",
         "product":93,
         "color":null,
         "size":null,
         "image_id":0,
         "quantity":20,
         "price":"53.99",
         "status":"True"
      }
   },
   {
      "model":"products.variants",
      "pk":78,
      "fields":{
         "title":"Designer Ladies Shirts Pink",
         "product":83,
         "color":120,
         "size":null,
         "image_id":356,
         "quantity":25,
         "price":"32.99",
         "status":"True"
      }
   },
   {
      "model":"products.variants",
      "pk":79,
      "fields":{
         "title":"Short body Hudi",
         "product":2,
         "color":null,
         "size":null,
         "image_id":0,
         "quantity":25,
         "price":"45.99",
         "status":"True"
      }
   },
   {
      "model":"products.variants",
      "pk":80,
      "fields":{
         "title":"Boys Shirts",
         "product":61,
         "color":null,
         "size":null,
         "image_id":0,
         "quantity":25,
         "price":"43.99",
         "status":"True"
      }
   },
   {
      "model":"products.variants",
      "pk":81,
      "fields":{
         "title":"Men Coats & Jackets",
         "product":120,
         "color":null,
         "size":null,
         "image_id":0,
         "quantity":20,
         "price":"53.99",
         "status":"True"
      }
   },
   {
      "model":"products.variants",
      "pk":85,
      "fields":{
         "title":"Hudi Boys",
         "product":127,
         "color":2,
         "size":null,
         "image_id":266,
         "quantity":33,
         "price":"30.99",
         "status":"True"
      }
   },
   {
      "model":"products.variants",
      "pk":86,
      "fields":{
         "title":"Hudi Boys",
         "product":127,
         "color":88,
         "size":null,
         "image_id":268,
         "quantity":38,
         "price":"40.99",
         "status":"True"
      }
   },
   {
      "model":"products.variants",
      "pk":87,
      "fields":{
         "title":"Men T-Shirts",
         "product":124,
         "color":null,
         "size":null,
         "image_id":0,
         "quantity":25,
         "price":"66.99",
         "status":"True"
      }
   },
   {
      "model":"products.variants",
      "pk":88,
      "fields":{
         "title":"Light Green check Shirt",
         "product":113,
         "color":113,
         "size":null,
         "image_id":280,
         "quantity":25,
         "price":"32.99",
         "status":"True"
      }
   },
   {
      "model":"products.variants",
      "pk":89,
      "fields":{
         "title":"Boys Hudi",
         "product":58,
         "color":null,
         "size":null,
         "image_id":0,
         "quantity":25,
         "price":"59.99",
         "status":"True"
      }
   },
   {
      "model":"products.variants",
      "pk":90,
      "fields":{
         "title":"Denim Jeans Blue",
         "product":110,
         "color":33,
         "size":null,
         "image_id":379,
         "quantity":20,
         "price":"24.99",
         "status":"True"
      }
   },
   {
      "model":"products.variants",
      "pk":91,
      "fields":{
         "title":"Men Shirts",
         "product":115,
         "color":null,
         "size":null,
         "image_id":0,
         "quantity":25,
         "price":"63.99",
         "status":"True"
      }
   },
   {
      "model":"products.variants",
      "pk":92,
      "fields":{
         "title":"Denim Jeans Blue Lighter Shade",
         "product":109,
         "color":33,
         "size":null,
         "image_id":382,
         "quantity":15,
         "price":"34.99",
         "status":"True"
      }
   },
   {
      "model":"products.variants",
      "pk":93,
      "fields":{
         "title":"Boys Hudi",
         "product":59,
         "color":null,
         "size":null,
         "image_id":0,
         "quantity":25,
         "price":"39.99",
         "status":"True"
      }
   },
   {
      "model":"products.variants",
      "pk":94,
      "fields":{
         "title":"Half Sleeve Men Sweaters Red",
         "product":99,
         "color":5,
         "size":null,
         "image_id":393,
         "quantity":25,
         "price":"15.99",
         "status":"True"
      }
   },
   {
      "model":"products.variants",
      "pk":95,
      "fields":{
         "title":"Girls Hudi",
         "product":129,
         "color":2,
         "size":null,
         "image_id":269,
         "quantity":45,
         "price":"52.99",
         "status":"True"
      }
   },
   {
      "model":"products.variants",
      "pk":96,
      "fields":{
         "title":"Hudi Light pink",
         "product":129,
         "color":111,
         "size":null,
         "image_id":271,
         "quantity":50,
         "price":"52.00",
         "status":"True"
      }
   },
   {
      "model":"products.variants",
      "pk":97,
      "fields":{
         "title":"Boys Damage Jeans",
         "product":73,
         "color":null,
         "size":null,
         "image_id":0,
         "quantity":25,
         "price":"33.99",
         "status":"True"
      }
   },
   {
      "model":"products.variants",
      "pk":98,
      "fields":{
         "title":"Stylish Ladies Dresses",
         "product":95,
         "color":null,
         "size":null,
         "image_id":0,
         "quantity":20,
         "price":"53.99",
         "status":"True"
      }
   },
   {
      "model":"products.variants",
      "pk":100,
      "fields":{
         "title":"Blue Sweater",
         "product":80,
         "color":33,
         "size":null,
         "image_id":365,
         "quantity":15,
         "price":"35.99",
         "status":"True"
      }
   },
   {
      "model":"products.variants",
      "pk":103,
      "fields":{
         "title":"Light Blue T-shirt",
         "product":130,
         "color":2,
         "size":1,
         "image_id":276,
         "quantity":25,
         "price":"52.99",
         "status":"True"
      }
   },
   {
      "model":"products.variants",
      "pk":107,
      "fields":{
         "title":"Black T-shirt",
         "product":130,
         "color":34,
         "size":2,
         "image_id":279,
         "quantity":32,
         "price":"23.99",
         "status":"True"
      }
   },
   {
      "model":"products.variants",
      "pk":108,
      "fields":{
         "title":"Blue T-shirt",
         "product":130,
         "color":33,
         "size":1,
         "image_id":277,
         "quantity":32,
         "price":"34.99",
         "status":"True"
      }
   },
   {
      "model":"products.variants",
      "pk":109,
      "fields":{
         "title":"Boys Jeans",
         "product":77,
         "color":null,
         "size":null,
         "image_id":0,
         "quantity":32,
         "price":"45.00",
         "status":"True"
      }
   },
   {
      "model":"products.variants",
      "pk":110,
      "fields":{
         "title":"Boys Damage Jeans",
         "product":72,
         "color":null,
         "size":null,
         "image_id":0,
         "quantity":25,
         "price":"32.99",
         "status":"True"
      }
   },
   {
      "model":"products.variants",
      "pk":111,
      "fields":{
         "title":"Classic Boys Hudi white",
         "product":56,
         "color":4,
         "size":2,
         "image_id":480,
         "quantity":15,
         "price":"23.99",
         "status":"True"
      }
   },
   {
      "model":"products.variants",
      "pk":112,
      "fields":{
         "title":"Grey Cardigan",
         "product":26,
         "color":null,
         "size":1,
         "image_id":367,
         "quantity":25,
         "price":"25.99",
         "status":"True"
      }
   },
   {
      "model":"products.variants",
      "pk":113,
      "fields":{
         "title":"Ladies Sweater & Cardigans",
         "product":24,
         "color":null,
         "size":null,
         "image_id":0,
         "quantity":25,
         "price":"59.99",
         "status":"True"
      }
   },
   {
      "model":"products.variants",
      "pk":114,
      "fields":{
         "title":"Classic Black Hudi",
         "product":1,
         "color":null,
         "size":null,
         "image_id":0,
         "quantity":25,
         "price":"53.99",
         "status":"True"
      }
   },
   {
      "model":"products.variants",
      "pk":115,
      "fields":{
         "title":"Clasic casual wear huddi",
         "product":10,
         "color":null,
         "size":null,
         "image_id":0,
         "quantity":25,
         "price":"43.99",
         "status":"True"
      }
   },
   {
      "model":"products.variants",
      "pk":116,
      "fields":{
         "title":"Ladies Tops - Black",
         "product":12,
         "color":34,
         "size":null,
         "image_id":321,
         "quantity":15,
         "price":"25.99",
         "status":"True"
      }
   },
   {
      "model":"products.variants",
      "pk":117,
      "fields":{
         "title":"Ladies Tops",
         "product":13,
         "color":null,
         "size":null,
         "image_id":0,
         "quantity":25,
         "price":"55.99",
         "status":"True"
      }
   },
   {
      "model":"products.variants",
      "pk":118,
      "fields":{
         "title":"Ladies Tops-Blue",
         "product":14,
         "color":33,
         "size":null,
         "image_id":317,
         "quantity":25,
         "price":"25.99",
         "status":"True"
      }
   },
   {
      "model":"products.variants",
      "pk":119,
      "fields":{
         "title":"Ladies Suits",
         "product":16,
         "color":null,
         "size":null,
         "image_id":0,
         "quantity":25,
         "price":"43.99",
         "status":"True"
      }
   },
   {
      "model":"products.variants",
      "pk":120,
      "fields":{
         "title":"Ladies Dress Green",
         "product":96,
         "color":118,
         "size":null,
         "image_id":323,
         "quantity":20,
         "price":"35.99",
         "status":"True"
      }
   },
   {
      "model":"products.variants",
      "pk":121,
      "fields":{
         "title":"Girls Tops",
         "product":41,
         "color":null,
         "size":null,
         "image_id":0,
         "quantity":25,
         "price":"53.99",
         "status":"True"
      }
   },
   {
      "model":"products.variants",
      "pk":122,
      "fields":{
         "title":"Stylish addid hudis",
         "product":9,
         "color":null,
         "size":null,
         "image_id":0,
         "quantity":25,
         "price":"63.99",
         "status":"True"
      }
   },
   {
      "model":"products.variants",
      "pk":123,
      "fields":{
         "title":"Girls Shirts",
         "product":11,
         "color":null,
         "size":null,
         "image_id":0,
         "quantity":25,
         "price":"53.99",
         "status":"True"
      }
   },
   {
      "model":"products.variants",
      "pk":124,
      "fields":{
         "title":"Girls Shirts",
         "product":30,
         "color":null,
         "size":null,
         "image_id":0,
         "quantity":25,
         "price":"43.99",
         "status":"True"
      }
   },
   {
      "model":"products.variants",
      "pk":125,
      "fields":{
         "title":"Girls Shirts",
         "product":29,
         "color":null,
         "size":null,
         "image_id":0,
         "quantity":25,
         "price":"39.99",
         "status":"True"
      }
   },
   {
      "model":"products.variants",
      "pk":126,
      "fields":{
         "title":"Girls Shirts",
         "product":28,
         "color":null,
         "size":null,
         "image_id":0,
         "quantity":25,
         "price":"59.99",
         "status":"True"
      }
   },
   {
      "model":"products.variants",
      "pk":127,
      "fields":{
         "title":"Girls Shirts",
         "product":27,
         "color":null,
         "size":null,
         "image_id":0,
         "quantity":25,
         "price":"45.99",
         "status":"True"
      }
   },
   {
      "model":"products.variants",
      "pk":128,
      "fields":{
         "title":"Sweat shirt Hudi",
         "product":7,
         "color":null,
         "size":null,
         "image_id":0,
         "quantity":25,
         "price":"32.99",
         "status":"True"
      }
   },
   {
      "model":"products.variants",
      "pk":129,
      "fields":{
         "title":"Stylish addidas hudi",
         "product":8,
         "color":null,
         "size":null,
         "image_id":0,
         "quantity":25,
         "price":"33.99",
         "status":"True"
      }
   },
   {
      "model":"products.variants",
      "pk":130,
      "fields":{
         "title":"Lingeries set Black with white ribbon",
         "product":85,
         "color":34,
         "size":null,
         "image_id":302,
         "quantity":10,
         "price":"105.99",
         "status":"True"
      }
   },
   {
      "model":"products.variants",
      "pk":131,
      "fields":{
         "title":"Green check Shirt",
         "product":113,
         "color":88,
         "size":null,
         "image_id":281,
         "quantity":1,
         "price":"32.99",
         "status":"True"
      }
   },
   {
      "model":"products.variants",
      "pk":132,
      "fields":{
         "title":"Blue Check Shirt",
         "product":113,
         "color":33,
         "size":null,
         "image_id":282,
         "quantity":1,
         "price":"39.99",
         "status":"True"
      }
   },
   {
      "model":"products.variants",
      "pk":133,
      "fields":{
         "title":"Mahroon half Sleeves shirt",
         "product":114,
         "color":114,
         "size":null,
         "image_id":283,
         "quantity":30,
         "price":"43.99",
         "status":"True"
      }
   },
   {
      "model":"products.variants",
      "pk":134,
      "fields":{
         "title":"Black half Sleeves shirt",
         "product":114,
         "color":34,
         "size":null,
         "image_id":284,
         "quantity":30,
         "price":"43.99",
         "status":"True"
      }
   },
   {
      "model":"products.variants",
      "pk":135,
      "fields":{
         "title":"Royal blue half Sleeves shirt",
         "product":114,
         "color":110,
         "size":null,
         "image_id":286,
         "quantity":30,
         "price":"43.99",
         "status":"True"
      }
   },
   {
      "model":"products.variants",
      "pk":136,
      "fields":{
         "title":"light blue half Sleeves shirt",
         "product":114,
         "color":33,
         "size":null,
         "image_id":285,
         "quantity":30,
         "price":"43.99",
         "status":"True"
      }
   },
   {
      "model":"products.variants",
      "pk":138,
      "fields":{
         "title":"Men Shirts",
         "product":116,
         "color":null,
         "size":1,
         "image_id":288,
         "quantity":20,
         "price":"54.99",
         "status":"True"
      }
   },
   {
      "model":"products.variants",
      "pk":139,
      "fields":{
         "title":"Men Shirts",
         "product":116,
         "color":null,
         "size":2,
         "image_id":288,
         "quantity":20,
         "price":"54.99",
         "status":"True"
      }
   },
   {
      "model":"products.variants",
      "pk":140,
      "fields":{
         "title":"Men Shirts",
         "product":116,
         "color":null,
         "size":3,
         "image_id":288,
         "quantity":20,
         "price":"54.99",
         "status":"True"
      }
   },
   {
      "model":"products.variants",
      "pk":141,
      "fields":{
         "title":"Men Shirts",
         "product":116,
         "color":null,
         "size":19,
         "image_id":288,
         "quantity":20,
         "price":"44.99",
         "status":"True"
      }
   },
   {
      "model":"products.variants",
      "pk":142,
      "fields":{
         "title":"Light Blue Stylish Night Wear",
         "product":88,
         "color":2,
         "size":null,
         "image_id":289,
         "quantity":15,
         "price":"52.99",
         "status":"True"
      }
   },
   {
      "model":"products.variants",
      "pk":143,
      "fields":{
         "title":"Grey Stylish Night Wear",
         "product":88,
         "color":115,
         "size":null,
         "image_id":290,
         "quantity":15,
         "price":"52.99",
         "status":"True"
      }
   },
   {
      "model":"products.variants",
      "pk":144,
      "fields":{
         "title":"Pink Stylish Night Wear",
         "product":88,
         "color":111,
         "size":null,
         "image_id":291,
         "quantity":15,
         "price":"54.99",
         "status":"True"
      }
   },
   {
      "model":"products.variants",
      "pk":145,
      "fields":{
         "title":"Classic Night Wear-Black",
         "product":87,
         "color":34,
         "size":2,
         "image_id":292,
         "quantity":20,
         "price":"53.99",
         "status":"True"
      }
   },
   {
      "model":"products.variants",
      "pk":146,
      "fields":{
         "title":"Classic Night Wear-White",
         "product":87,
         "color":4,
         "size":2,
         "image_id":294,
         "quantity":20,
         "price":"53.99",
         "status":"True"
      }
   },
   {
      "model":"products.variants",
      "pk":147,
      "fields":{
         "title":"Classic Night Wear-GRey",
         "product":87,
         "color":115,
         "size":2,
         "image_id":293,
         "quantity":20,
         "price":"53.99",
         "status":"True"
      }
   },
   {
      "model":"products.variants",
      "pk":148,
      "fields":{
         "title":"Classic Night Wear-Black",
         "product":87,
         "color":34,
         "size":3,
         "image_id":292,
         "quantity":20,
         "price":"53.99",
         "status":"True"
      }
   },
   {
      "model":"products.variants",
      "pk":149,
      "fields":{
         "title":"Classic Night Wear-White",
         "product":87,
         "color":4,
         "size":3,
         "image_id":294,
         "quantity":20,
         "price":"53.99",
         "status":"True"
      }
   },
   {
      "model":"products.variants",
      "pk":150,
      "fields":{
         "title":"Classic Night Wear-Black",
         "product":87,
         "color":115,
         "size":3,
         "image_id":293,
         "quantity":20,
         "price":"53.99",
         "status":"True"
      }
   },
   {
      "model":"products.variants",
      "pk":151,
      "fields":{
         "title":"Classic Night Wear-Black",
         "product":87,
         "color":34,
         "size":1,
         "image_id":292,
         "quantity":20,
         "price":"53.99",
         "status":"True"
      }
   },
   {
      "model":"products.variants",
      "pk":152,
      "fields":{
         "title":"Classic Night Wear-White",
         "product":87,
         "color":4,
         "size":1,
         "image_id":294,
         "quantity":20,
         "price":"53.99",
         "status":"True"
      }
   },
   {
      "model":"products.variants",
      "pk":153,
      "fields":{
         "title":"Classic Night Wear-Black",
         "product":87,
         "color":115,
         "size":1,
         "image_id":293,
         "quantity":20,
         "price":"53.99",
         "status":"True"
      }
   },
   {
      "model":"products.variants",
      "pk":154,
      "fields":{
         "title":"Stylish Lingeires-White",
         "product":86,
         "color":4,
         "size":null,
         "image_id":297,
         "quantity":15,
         "price":"42.99",
         "status":"True"
      }
   },
   {
      "model":"products.variants",
      "pk":155,
      "fields":{
         "title":"Stylish Lingeries-Black",
         "product":86,
         "color":34,
         "size":null,
         "image_id":295,
         "quantity":15,
         "price":"42.99",
         "status":"True"
      }
   },
   {
      "model":"products.variants",
      "pk":156,
      "fields":{
         "title":"Stylish Lingeries-Light Pink",
         "product":86,
         "color":111,
         "size":null,
         "image_id":296,
         "quantity":15,
         "price":"42.99",
         "status":"True"
      }
   },
   {
      "model":"products.variants",
      "pk":157,
      "fields":{
         "title":"Lingeries set off-white",
         "product":85,
         "color":116,
         "size":null,
         "image_id":300,
         "quantity":10,
         "price":"105.99",
         "status":"True"
      }
   },
   {
      "model":"products.variants",
      "pk":158,
      "fields":{
         "title":"Lingeries set light-blue",
         "product":85,
         "color":2,
         "size":null,
         "image_id":300,
         "quantity":10,
         "price":"105.99",
         "status":"True"
      }
   },
   {
      "model":"products.variants",
      "pk":159,
      "fields":{
         "title":"Lingeries set white",
         "product":85,
         "color":4,
         "size":null,
         "image_id":299,
         "quantity":10,
         "price":"105.99",
         "status":"True"
      }
   },
   {
      "model":"products.variants",
      "pk":160,
      "fields":{
         "title":"Lingeries set black",
         "product":85,
         "color":34,
         "size":null,
         "image_id":298,
         "quantity":10,
         "price":"105.99",
         "status":"True"
      }
   },
   {
      "model":"products.variants",
      "pk":161,
      "fields":{
         "title":"Party Wear Shirt",
         "product":84,
         "color":null,
         "size":null,
         "image_id":314,
         "quantity":25,
         "price":"23.00",
         "status":"True"
      }
   },
   {
      "model":"products.variants",
      "pk":162,
      "fields":{
         "title":"Girls Tops",
         "product":42,
         "color":null,
         "size":null,
         "image_id":0,
         "quantity":25,
         "price":"32.99",
         "status":"True"
      }
   },
   {
      "model":"products.variants",
      "pk":163,
      "fields":{
         "title":"Ladies Tops-Purple",
         "product":14,
         "color":101,
         "size":null,
         "image_id":320,
         "quantity":25,
         "price":"25.99",
         "status":"True"
      }
   },
   {
      "model":"products.variants",
      "pk":164,
      "fields":{
         "title":"Ladies Tops Sea-green",
         "product":12,
         "color":117,
         "size":null,
         "image_id":322,
         "quantity":15,
         "price":"25.99",
         "status":"True"
      }
   },
   {
      "model":"products.variants",
      "pk":165,
      "fields":{
         "title":"Ladies Dress Yellow",
         "product":96,
         "color":88,
         "size":null,
         "image_id":324,
         "quantity":20,
         "price":"35.99",
         "status":"True"
      }
   },
   {
      "model":"products.variants",
      "pk":166,
      "fields":{
         "title":"Check Print Black-White",
         "product":118,
         "color":34,
         "size":null,
         "image_id":330,
         "quantity":45,
         "price":"78.00",
         "status":"True"
      }
   },
   {
      "model":"products.variants",
      "pk":167,
      "fields":{
         "title":"Check Print Plain brown shade",
         "product":118,
         "color":119,
         "size":null,
         "image_id":331,
         "quantity":45,
         "price":"78.00",
         "status":"True"
      }
   },
   {
      "model":"products.variants",
      "pk":168,
      "fields":{
         "title":"Men Coat Black",
         "product":117,
         "color":34,
         "size":null,
         "image_id":0,
         "quantity":32,
         "price":"42.99",
         "status":"True"
      }
   },
   {
      "model":"products.variants",
      "pk":169,
      "fields":{
         "title":"Men Coat Green shade",
         "product":117,
         "color":88,
         "size":null,
         "image_id":0,
         "quantity":23,
         "price":"42.99",
         "status":"True"
      }
   },
   {
      "model":"products.variants",
      "pk":170,
      "fields":{
         "title":"Men Coat Black",
         "product":119,
         "color":34,
         "size":null,
         "image_id":334,
         "quantity":20,
         "price":"53.99",
         "status":"True"
      }
   },
   {
      "model":"products.variants",
      "pk":171,
      "fields":{
         "title":"Men Coat Green",
         "product":119,
         "color":88,
         "size":null,
         "image_id":335,
         "quantity":1,
         "price":"0.00",
         "status":"True"
      }
   },
   {
      "model":"products.variants",
      "pk":172,
      "fields":{
         "title":"Ladies Coats",
         "product":20,
         "color":null,
         "size":null,
         "image_id":0,
         "quantity":25,
         "price":"60.99",
         "status":"True"
      }
   },
   {
      "model":"products.variants",
      "pk":173,
      "fields":{
         "title":"Ladies Coat",
         "product":23,
         "color":34,
         "size":1,
         "image_id":336,
         "quantity":15,
         "price":"65.99",
         "status":"True"
      }
   },
   {
      "model":"products.variants",
      "pk":174,
      "fields":{
         "title":"Ladies Coat",
         "product":23,
         "color":116,
         "size":1,
         "image_id":337,
         "quantity":15,
         "price":"65.99",
         "status":"True"
      }
   },
   {
      "model":"products.variants",
      "pk":175,
      "fields":{
         "title":"Ladies Coat",
         "product":23,
         "color":34,
         "size":3,
         "image_id":336,
         "quantity":15,
         "price":"65.99",
         "status":"True"
      }
   },
   {
      "model":"products.variants",
      "pk":176,
      "fields":{
         "title":"Ladies Coat",
         "product":23,
         "color":116,
         "size":3,
         "image_id":337,
         "quantity":15,
         "price":"65.99",
         "status":"True"
      }
   },
   {
      "model":"products.variants",
      "pk":177,
      "fields":{
         "title":"Ladies Coat",
         "product":23,
         "color":34,
         "size":2,
         "image_id":336,
         "quantity":15,
         "price":"65.99",
         "status":"True"
      }
   },
   {
      "model":"products.variants",
      "pk":178,
      "fields":{
         "title":"Ladies Coat",
         "product":23,
         "color":116,
         "size":2,
         "image_id":337,
         "quantity":15,
         "price":"65.99",
         "status":"True"
      }
   },
   {
      "model":"products.variants",
      "pk":179,
      "fields":{
         "title":"Ladies Jackets",
         "product":22,
         "color":null,
         "size":null,
         "image_id":0,
         "quantity":25,
         "price":"83.99",
         "status":"True"
      }
   },
   {
      "model":"products.variants",
      "pk":180,
      "fields":{
         "title":"Ladies Jacket",
         "product":21,
         "color":null,
         "size":null,
         "image_id":0,
         "quantity":25,
         "price":"43.99",
         "status":"True"
      }
   },
   {
      "model":"products.variants",
      "pk":181,
      "fields":{
         "title":"Stylish Ladies Jeans- Blue",
         "product":92,
         "color":33,
         "size":null,
         "image_id":341,
         "quantity":20,
         "price":"33.99",
         "status":"True"
      }
   },
   {
      "model":"products.variants",
      "pk":182,
      "fields":{
         "title":"Stylish Ladies Jeans Light-blue",
         "product":92,
         "color":2,
         "size":null,
         "image_id":342,
         "quantity":20,
         "price":"33.99",
         "status":"True"
      }
   },
   {
      "model":"products.variants",
      "pk":183,
      "fields":{
         "title":"Stylish Ladies Jeans Black",
         "product":92,
         "color":34,
         "size":null,
         "image_id":343,
         "quantity":20,
         "price":"33.99",
         "status":"True"
      }
   },
   {
      "model":"products.variants",
      "pk":184,
      "fields":{
         "title":"Stylish Ladies Jeans Blue shade",
         "product":92,
         "color":33,
         "size":null,
         "image_id":344,
         "quantity":20,
         "price":"33.99",
         "status":"True"
      }
   },
   {
      "model":"products.variants",
      "pk":185,
      "fields":{
         "title":"Stylish Ladies Jeans Blue Shade",
         "product":92,
         "color":110,
         "size":null,
         "image_id":345,
         "quantity":20,
         "price":"33.99",
         "status":"True"
      }
   },
   {
      "model":"products.variants",
      "pk":186,
      "fields":{
         "title":"Stylish Ladies Jeans Grey Shade",
         "product":92,
         "color":115,
         "size":null,
         "image_id":346,
         "quantity":20,
         "price":"33.99",
         "status":"True"
      }
   },
   {
      "model":"products.variants",
      "pk":187,
      "fields":{
         "title":"Ladies Jeans Blue Shade",
         "product":89,
         "color":33,
         "size":null,
         "image_id":348,
         "quantity":20,
         "price":"22.99",
         "status":"True"
      }
   },
   {
      "model":"products.variants",
      "pk":188,
      "fields":{
         "title":"Ladies Jeans Blue Shade",
         "product":89,
         "color":33,
         "size":null,
         "image_id":349,
         "quantity":20,
         "price":"22.99",
         "status":"True"
      }
   },
   {
      "model":"products.variants",
      "pk":189,
      "fields":{
         "title":"Ladies Jeans Blue Shade",
         "product":89,
         "color":33,
         "size":null,
         "image_id":350,
         "quantity":20,
         "price":"22.99",
         "status":"True"
      }
   },
   {
      "model":"products.variants",
      "pk":190,
      "fields":{
         "title":"Ladies Jeans Blue Shade",
         "product":89,
         "color":33,
         "size":null,
         "image_id":351,
         "quantity":20,
         "price":"22.99",
         "status":"True"
      }
   },
   {
      "model":"products.variants",
      "pk":191,
      "fields":{
         "title":"Ladies Jeans Black",
         "product":90,
         "color":34,
         "size":null,
         "image_id":352,
         "quantity":20,
         "price":"34.99",
         "status":"True"
      }
   },
   {
      "model":"products.variants",
      "pk":192,
      "fields":{
         "title":"Old look Jeans Grey",
         "product":91,
         "color":115,
         "size":null,
         "image_id":347,
         "quantity":20,
         "price":"25.99",
         "status":"True"
      }
   },
   {
      "model":"products.variants",
      "pk":193,
      "fields":{
         "title":"Ladies Jeans Blue",
         "product":90,
         "color":33,
         "size":null,
         "image_id":353,
         "quantity":20,
         "price":"34.99",
         "status":"True"
      }
   },
   {
      "model":"products.variants",
      "pk":194,
      "fields":{
         "title":"Old look Jeans Black",
         "product":91,
         "color":34,
         "size":null,
         "image_id":354,
         "quantity":20,
         "price":"25.99",
         "status":"True"
      }
   },
   {
      "model":"products.variants",
      "pk":195,
      "fields":{
         "title":"Old look Jeans Blue",
         "product":91,
         "color":33,
         "size":null,
         "image_id":355,
         "quantity":20,
         "price":"25.99",
         "status":"True"
      }
   },
   {
      "model":"products.variants",
      "pk":196,
      "fields":{
         "title":"Ladies Shirts Pink",
         "product":81,
         "color":5,
         "size":null,
         "image_id":363,
         "quantity":25,
         "price":"32.99",
         "status":"True"
      }
   },
   {
      "model":"products.variants",
      "pk":197,
      "fields":{
         "title":"Ladies Shirts Blue",
         "product":81,
         "color":33,
         "size":null,
         "image_id":364,
         "quantity":25,
         "price":"32.99",
         "status":"True"
      }
   },
   {
      "model":"products.variants",
      "pk":198,
      "fields":{
         "title":"Designer Ladies Shirts Blue shade",
         "product":83,
         "color":110,
         "size":null,
         "image_id":357,
         "quantity":25,
         "price":"32.99",
         "status":"True"
      }
   },
   {
      "model":"products.variants",
      "pk":199,
      "fields":{
         "title":"Designer Ladies Shirts Blue shade",
         "product":83,
         "color":33,
         "size":null,
         "image_id":358,
         "quantity":25,
         "price":"32.99",
         "status":"True"
      }
   },
   {
      "model":"products.variants",
      "pk":200,
      "fields":{
         "title":"Designer Ladies Shirts Blue shade",
         "product":83,
         "color":2,
         "size":null,
         "image_id":359,
         "quantity":25,
         "price":"32.99",
         "status":"True"
      }
   },
   {
      "model":"products.variants",
      "pk":201,
      "fields":{
         "title":"Maroon Sweater",
         "product":80,
         "color":114,
         "size":null,
         "image_id":366,
         "quantity":15,
         "price":"35.99",
         "status":"True"
      }
   },
   {
      "model":"products.variants",
      "pk":202,
      "fields":{
         "title":"Grey Cardigan",
         "product":26,
         "color":null,
         "size":2,
         "image_id":367,
         "quantity":25,
         "price":"25.99",
         "status":"True"
      }
   },
   {
      "model":"products.variants",
      "pk":203,
      "fields":{
         "title":"Grey Cardigan",
         "product":26,
         "color":null,
         "size":3,
         "image_id":367,
         "quantity":25,
         "price":"25.99",
         "status":"True"
      }
   },
   {
      "model":"products.variants",
      "pk":204,
      "fields":{
         "title":"Grey Cardigan",
         "product":26,
         "color":null,
         "size":10,
         "image_id":367,
         "quantity":25,
         "price":"25.99",
         "status":"True"
      }
   },
   {
      "model":"products.variants",
      "pk":205,
      "fields":{
         "title":"Grey Cardigan",
         "product":26,
         "color":null,
         "size":19,
         "image_id":367,
         "quantity":25,
         "price":"25.99",
         "status":"True"
      }
   },
   {
      "model":"products.variants",
      "pk":206,
      "fields":{
         "title":"Maroon Half Sleeves Sweater",
         "product":25,
         "color":114,
         "size":null,
         "image_id":370,
         "quantity":25,
         "price":"19.99",
         "status":"True"
      }
   },
   {
      "model":"products.variants",
      "pk":207,
      "fields":{
         "title":"Men T-Shirts",
         "product":103,
         "color":null,
         "size":null,
         "image_id":0,
         "quantity":25,
         "price":"52.99",
         "status":"True"
      }
   },
   {
      "model":"products.variants",
      "pk":208,
      "fields":{
         "title":"Denim Jeans Blue Darker Shade",
         "product":109,
         "color":33,
         "size":null,
         "image_id":383,
         "quantity":15,
         "price":"34.99",
         "status":"True"
      }
   },
   {
      "model":"products.variants",
      "pk":209,
      "fields":{
         "title":"Denim Jeans Black",
         "product":110,
         "color":34,
         "size":null,
         "image_id":380,
         "quantity":20,
         "price":"24.99",
         "status":"True"
      }
   },
   {
      "model":"products.variants",
      "pk":210,
      "fields":{
         "title":"Denim Jeans Grey",
         "product":110,
         "color":115,
         "size":null,
         "image_id":381,
         "quantity":20,
         "price":"24.99",
         "status":"True"
      }
   },
   {
      "model":"products.variants",
      "pk":211,
      "fields":{
         "title":"Denim Jeans",
         "product":111,
         "color":null,
         "size":null,
         "image_id":0,
         "quantity":25,
         "price":"20.99",
         "status":"True"
      }
   },
   {
      "model":"products.variants",
      "pk":212,
      "fields":{
         "title":"Fitted Denim Jeans Blue",
         "product":112,
         "color":33,
         "size":null,
         "image_id":376,
         "quantity":24,
         "price":"25.99",
         "status":"True"
      }
   },
   {
      "model":"products.variants",
      "pk":213,
      "fields":{
         "title":"Fitted Denim Jeans Black",
         "product":112,
         "color":34,
         "size":null,
         "image_id":377,
         "quantity":24,
         "price":"25.99",
         "status":"True"
      }
   },
   {
      "model":"products.variants",
      "pk":214,
      "fields":{
         "title":"Men Sweaters Grey",
         "product":100,
         "color":115,
         "size":null,
         "image_id":396,
         "quantity":1,
         "price":"25.99",
         "status":"True"
      }
   },
   {
      "model":"products.variants",
      "pk":215,
      "fields":{
         "title":"Men Sweaters Black",
         "product":100,
         "color":34,
         "size":null,
         "image_id":397,
         "quantity":1,
         "price":"25.99",
         "status":"True"
      }
   },
   {
      "model":"products.variants",
      "pk":216,
      "fields":{
         "title":"Men Sweaters Black",
         "product":100,
         "color":33,
         "size":null,
         "image_id":398,
         "quantity":1,
         "price":"25.99",
         "status":"True"
      }
   },
   {
      "model":"products.variants",
      "pk":217,
      "fields":{
         "title":"Half Sleeve Men Sweaters Blue",
         "product":99,
         "color":33,
         "size":null,
         "image_id":394,
         "quantity":25,
         "price":"15.99",
         "status":"True"
      }
   },
   {
      "model":"products.variants",
      "pk":218,
      "fields":{
         "title":"Half Sleeve Men Sweaters Grey",
         "product":99,
         "color":115,
         "size":null,
         "image_id":395,
         "quantity":25,
         "price":"15.99",
         "status":"True"
      }
   },
   {
      "model":"products.variants",
      "pk":219,
      "fields":{
         "title":"Men Sweaters & Cardigans",
         "product":98,
         "color":null,
         "size":null,
         "image_id":0,
         "quantity":25,
         "price":"55.99",
         "status":"True"
      }
   },
   {
      "model":"products.variants",
      "pk":220,
      "fields":{
         "title":"Men Designer Sweater",
         "product":97,
         "color":110,
         "size":null,
         "image_id":390,
         "quantity":15,
         "price":"45.99",
         "status":"True"
      }
   },
   {
      "model":"products.variants",
      "pk":221,
      "fields":{
         "title":"Men Designer Sweater",
         "product":97,
         "color":115,
         "size":null,
         "image_id":391,
         "quantity":15,
         "price":"45.99",
         "status":"True"
      }
   },
   {
      "model":"products.variants",
      "pk":222,
      "fields":{
         "title":"Boys Jeans",
         "product":78,
         "color":null,
         "size":null,
         "image_id":0,
         "quantity":23,
         "price":"32.00",
         "status":"True"
      }
   },
   {
      "model":"products.variants",
      "pk":223,
      "fields":{
         "title":"Girls Jeans",
         "product":52,
         "color":null,
         "size":null,
         "image_id":0,
         "quantity":25,
         "price":"32.99",
         "status":"True"
      }
   },
   {
      "model":"products.variants",
      "pk":224,
      "fields":{
         "title":"Girls Jeans",
         "product":55,
         "color":null,
         "size":null,
         "image_id":0,
         "quantity":25,
         "price":"43.99",
         "status":"True"
      }
   },
   {
      "model":"products.variants",
      "pk":225,
      "fields":{
         "title":"Girls Damage Jeans",
         "product":48,
         "color":null,
         "size":null,
         "image_id":0,
         "quantity":25,
         "price":"29.99",
         "status":"True"
      }
   },
   {
      "model":"products.variants",
      "pk":226,
      "fields":{
         "title":"Girls Damage Jeans",
         "product":50,
         "color":null,
         "size":null,
         "image_id":0,
         "quantity":25,
         "price":"23.99",
         "status":"True"
      }
   },
   {
      "model":"products.variants",
      "pk":227,
      "fields":{
         "title":"Boys Shirts",
         "product":63,
         "color":null,
         "size":null,
         "image_id":0,
         "quantity":25,
         "price":"66.99",
         "status":"True"
      }
   },
   {
      "model":"products.variants",
      "pk":228,
      "fields":{
         "title":"Girls Coats & Jackets",
         "product":40,
         "color":null,
         "size":null,
         "image_id":0,
         "quantity":25,
         "price":"43.99",
         "status":"True"
      }
   },
   {
      "model":"products.variants",
      "pk":229,
      "fields":{
         "title":"Girls Coats & Jackets",
         "product":39,
         "color":null,
         "size":null,
         "image_id":0,
         "quantity":25,
         "price":"39.99",
         "status":"True"
      }
   },
   {
      "model":"products.variants",
      "pk":230,
      "fields":{
         "title":"Girls Coats & Jackets",
         "product":36,
         "color":null,
         "size":null,
         "image_id":0,
         "quantity":25,
         "price":"53.99",
         "status":"True"
      }
   },
   {
      "model":"products.variants",
      "pk":231,
      "fields":{
         "title":"Girls Skin fitted trouser",
         "product":47,
         "color":null,
         "size":null,
         "image_id":0,
         "quantity":25,
         "price":"25.99",
         "status":"True"
      }
   },
   {
      "model":"products.variants",
      "pk":232,
      "fields":{
         "title":"Girl Fitted Trouser Black",
         "product":46,
         "color":34,
         "size":null,
         "image_id":429,
         "quantity":25,
         "price":"22.99",
         "status":"True"
      }
   },
   {
      "model":"products.variants",
      "pk":233,
      "fields":{
         "title":"Girls fitted trousers off white",
         "product":49,
         "color":116,
         "size":null,
         "image_id":417,
         "quantity":45,
         "price":"19.99",
         "status":"True"
      }
   },
   {
      "model":"products.variants",
      "pk":234,
      "fields":{
         "title":"Girls fitted trousers white",
         "product":49,
         "color":4,
         "size":null,
         "image_id":418,
         "quantity":45,
         "price":"19.99",
         "status":"True"
      }
   },
   {
      "model":"products.variants",
      "pk":235,
      "fields":{
         "title":"Girls fitted trousers Black mustard",
         "product":49,
         "color":122,
         "size":null,
         "image_id":419,
         "quantity":45,
         "price":"19.99",
         "status":"True"
      }
   },
   {
      "model":"products.variants",
      "pk":236,
      "fields":{
         "title":"Girls fitted trousers Blue",
         "product":49,
         "color":33,
         "size":null,
         "image_id":420,
         "quantity":45,
         "price":"19.99",
         "status":"True"
      }
   },
   {
      "model":"products.variants",
      "pk":237,
      "fields":{
         "title":"Girls fitted trousers Pink",
         "product":49,
         "color":120,
         "size":null,
         "image_id":421,
         "quantity":45,
         "price":"19.99",
         "status":"True"
      }
   },
   {
      "model":"products.variants",
      "pk":238,
      "fields":{
         "title":"Girls fitted trousers green",
         "product":49,
         "color":118,
         "size":null,
         "image_id":422,
         "quantity":45,
         "price":"19.99",
         "status":"True"
      }
   },
   {
      "model":"products.variants",
      "pk":239,
      "fields":{
         "title":"Girls fitted trousers green",
         "product":49,
         "color":88,
         "size":null,
         "image_id":423,
         "quantity":45,
         "price":"19.99",
         "status":"True"
      }
   },
   {
      "model":"products.variants",
      "pk":240,
      "fields":{
         "title":"Girls fitted trousers light Blue",
         "product":49,
         "color":2,
         "size":null,
         "image_id":424,
         "quantity":45,
         "price":"19.99",
         "status":"True"
      }
   },
   {
      "model":"products.variants",
      "pk":241,
      "fields":{
         "title":"Girls fitted trousers Marganda",
         "product":49,
         "color":121,
         "size":null,
         "image_id":425,
         "quantity":45,
         "price":"19.99",
         "status":"True"
      }
   },
   {
      "model":"products.variants",
      "pk":242,
      "fields":{
         "title":"Girl Fitted Trouser Blue",
         "product":46,
         "color":33,
         "size":null,
         "image_id":430,
         "quantity":25,
         "price":"22.99",
         "status":"True"
      }
   },
   {
      "model":"products.variants",
      "pk":243,
      "fields":{
         "title":"Girl Fitted Trouser Royal Blue",
         "product":46,
         "color":110,
         "size":null,
         "image_id":431,
         "quantity":25,
         "price":"22.99",
         "status":"True"
      }
   },
   {
      "model":"products.variants",
      "pk":244,
      "fields":{
         "title":"Girls Jeans",
         "product":53,
         "color":null,
         "size":null,
         "image_id":0,
         "quantity":25,
         "price":"33.99",
         "status":"True"
      }
   },
   {
      "model":"products.variants",
      "pk":245,
      "fields":{
         "title":"Ladies Skirt and Shirt",
         "product":17,
         "color":null,
         "size":null,
         "image_id":0,
         "quantity":25,
         "price":"45.99",
         "status":"True"
      }
   },
   {
      "model":"products.variants",
      "pk":246,
      "fields":{
         "title":"Boys Shirts",
         "product":60,
         "color":null,
         "size":null,
         "image_id":0,
         "quantity":25,
         "price":"13.99",
         "status":"True"
      }
   },
   {
      "model":"products.variants",
      "pk":247,
      "fields":{
         "title":"Classic Boys Hudi pink",
         "product":56,
         "color":120,
         "size":2,
         "image_id":481,
         "quantity":15,
         "price":"23.99",
         "status":"True"
      }
   },
   {
      "model":"products.variants",
      "pk":248,
      "fields":{
         "title":"Classic Boys Hudi white",
         "product":56,
         "color":4,
         "size":3,
         "image_id":480,
         "quantity":15,
         "price":"23.99",
         "status":"True"
      }
   },
   {
      "model":"products.variants",
      "pk":249,
      "fields":{
         "title":"Classic Boys Hudi pink",
         "product":56,
         "color":120,
         "size":3,
         "image_id":481,
         "quantity":15,
         "price":"23.99",
         "status":"True"
      }
   },
   {
      "model":"products.variants",
      "pk":250,
      "fields":{
         "title":"Classic Boys Hudi white",
         "product":56,
         "color":4,
         "size":1,
         "image_id":480,
         "quantity":15,
         "price":"23.99",
         "status":"True"
      }
   },
   {
      "model":"products.variants",
      "pk":251,
      "fields":{
         "title":"Classic Boys Hudi pink",
         "product":56,
         "color":120,
         "size":1,
         "image_id":481,
         "quantity":15,
         "price":"23.99",
         "status":"True"
      }
   },
   {
      "model":"products.variants",
      "pk":252,
      "fields":{
         "title":"Classic Boys Hudi white",
         "product":56,
         "color":4,
         "size":10,
         "image_id":480,
         "quantity":15,
         "price":"23.99",
         "status":"True"
      }
   },
   {
      "model":"products.variants",
      "pk":253,
      "fields":{
         "title":"Classic Boys Hudi pink",
         "product":56,
         "color":120,
         "size":10,
         "image_id":481,
         "quantity":15,
         "price":"23.99",
         "status":"True"
      }
   }
]