[
   {
      "pk":11,
      "model":"products.product",
      "fields":{
         "title":"Girls Shirts",
         "description":"Classic Girls Shirts",
         "image":"media/pk_1.jpg",
         "price":53.99,
         "quantity":25,
         "detail":"classic something",
         "status":true,
         "create_at":"2020-10-25 10:42:07.596776",
         "update_at":"2020-11-25 17:03:03.625972",
         "category_id":2,
         "variant":"None",
         "has_variant":false,
         "new_edition":true,
         "discount_30_percent":false,
         "rate":4.6
      }
   },
   {
      "pk":27,
      "model":"products.product",
      "fields":{
         "title":"Girls Shirts",
         "description":"Elegant Girls Shirts",
         "image":"media/pk_2.jpg",
         "price":45.99,
         "quantity":25,
         "detail":"classic something",
         "status":true,
         "create_at":"2020-10-25 10:42:07.596776",
         "update_at":"2020-11-25 17:03:03.625972",
         "category_id":2,
         "variant":"None",
         "has_variant":false,
         "new_edition":false,
         "discount_30_percent":false,
         "rate":5
      }
   },
   {
      "pk":28,
      "model":"products.product",
      "fields":{
         "title":"Girls Shirts",
         "description":"Casual Girls Shirts",
         "image":"media/pk_3.jpg",
         "price":59.99,
         "quantity":25,
         "detail":"classic something",
         "status":true,
         "create_at":"2020-10-25 10:42:07.596776",
         "update_at":"2020-11-25 17:03:03.625972",
         "category_id":2,
         "variant":"None",
         "has_variant":false,
         "new_edition":true,
         "discount_30_percent":false,
         "rate":4.6
      }
   },
   {
      "pk":29,
      "model":"products.product",
      "fields":{
         "title":"Girls Shirts",
         "description":"Soft Fabric Girls Shirts",
         "image":"media/pk_4.jpg",
         "price":39.99,
         "quantity":25,
         "detail":"classic something",
         "status":true,
         "create_at":"2020-10-25 10:42:07.596776",
         "update_at":"2020-11-25 17:03:03.625972",
         "category_id":2,
         "variant":"None",
         "has_variant":false,
         "new_edition":true,
         "discount_30_percent":false,
         "rate":4.6
      }
   },
   {
      "pk":30,
      "model":"products.product",
      "fields":{
         "title":"Girls Shirts",
         "description":"Slim Fit Girls Shirts",
         "image":"media/pk_5.jpg",
         "price":43.99,
         "quantity":25,
         "detail":"classic something",
         "status":true,
         "create_at":"2020-10-25 10:42:07.596776",
         "update_at":"2020-11-25 17:03:03.625972",
         "category_id":2,
         "variant":"None",
         "has_variant":false,
         "new_edition":true,
         "discount_30_percent":false,
         "rate":4.6
      }
   },
   {
      "pk":31,
      "model":"products.product",
      "fields":{
         "title":"Girls Dresses",
         "description":"Girls Designer Dresses",
         "image":"media/pk_6.jpg",
         "price":53.99,
         "quantity":25,
         "detail":"classic something",
         "status":true,
         "create_at":"2020-10-25 10:42:07.596776",
         "update_at":"2020-11-25 17:03:03.625972",
         "category_id":3,
         "variant":"None",
         "has_variant":false,
         "new_edition":true,
         "discount_30_percent":false,
         "rate":4.6
      }
   },
   {
      "pk":32,
      "model":"products.product",
      "fields":{
         "title":"Girls Dresses",
         "description":"Girls Designer Dresses",
         "image":"media/pk_7.jpg",
         "price":32.99,
         "quantity":25,
         "detail":"classic something",
         "status":true,
         "create_at":"2020-10-25 10:42:07.596776",
         "update_at":"2020-11-25 17:03:03.625972",
         "category_id":3,
         "variant":"None",
         "has_variant":false,
         "new_edition":true,
         "discount_30_percent":false,
         "rate":4.6
      }
   },
   {
      "pk":33,
      "model":"products.product",
      "fields":{
         "title":"Girls Dresses",
         "description":"Girls Designer Dresses",
         "image":"media/pk_8.jpg",
         "price":33.99,
         "quantity":25,
         "detail":"classic something",
         "status":true,
         "create_at":"2020-10-25 10:42:07.596776",
         "update_at":"2020-11-25 17:03:03.625972",
         "category_id":3,
         "variant":"None",
         "has_variant":false,
         "new_edition":true,
         "discount_30_percent":false,
         "rate":4.6
      }
   },
   {
      "pk":34,
      "model":"products.product",
      "fields":{
         "title":"Girls Dresses",
         "description":"Girls Designer Dresses",
         "image":"media/pk_9.jpg",
         "price":63.99,
         "quantity":25,
         "detail":"classic something",
         "status":true,
         "create_at":"2020-10-25 10:42:07.596776",
         "update_at":"2020-11-25 17:03:03.625972",
         "category_id":3,
         "variant":"None",
         "has_variant":false,
         "new_edition":true,
         "discount_30_percent":false,
         "rate":4.6
      }
   },
   {
      "pk":35,
      "model":"products.product",
      "fields":{
         "title":"Girls Dresses",
         "description":"Girls Designer Dresses",
         "image":"media/pk_10.jpg",
         "price":43.99,
         "quantity":25,
         "detail":"classic something",
         "status":true,
         "create_at":"2020-10-25 10:42:07.596776",
         "update_at":"2020-11-25 17:03:03.625972",
         "category_id":3,
         "variant":"None",
         "has_variant":false,
         "new_edition":true,
         "discount_30_percent":false,
         "rate":4.6
      }
   },
   {
      "pk":36,
      "model":"products.product",
      "fields":{
         "title":"Girls Coats & Jackets",
         "description":"Girls Designer Coats & Jackets",
         "image":"media/pk_1.jpg",
         "price":53.99,
         "quantity":25,
         "detail":"classic something",
         "status":true,
         "create_at":"2020-10-25 10:42:07.596776",
         "update_at":"2020-11-25 17:03:03.625972",
         "category_id":4,
         "variant":"None",
         "has_variant":false,
         "new_edition":true,
         "discount_30_percent":false,
         "rate":4.6
      }
   },
   {
      "pk":37,
      "model":"products.product",
      "fields":{
         "title":"Girls Coats & Jackets",
         "description":"Girls Designer Coats & Jackets",
         "image":"media/pk_2.jpg",
         "price":45.99,
         "quantity":25,
         "detail":"classic something",
         "status":true,
         "create_at":"2020-10-25 10:42:07.596776",
         "update_at":"2020-11-25 17:03:03.625972",
         "category_id":4,
         "variant":"None",
         "has_variant":false,
         "new_edition":false,
         "discount_30_percent":false,
         "rate":5
      }
   },
   {
      "pk":38,
      "model":"products.product",
      "fields":{
         "title":"Girls Coats & Jackets",
         "description":"Girls Designer Coats & Jackets",
         "image":"media/pk_3.jpg",
         "price":59.99,
         "quantity":25,
         "detail":"classic something",
         "status":true,
         "create_at":"2020-10-25 10:42:07.596776",
         "update_at":"2020-11-25 17:03:03.625972",
         "category_id":4,
         "variant":"None",
         "has_variant":false,
         "new_edition":true,
         "discount_30_percent":false,
         "rate":4.6
      }
   },
   {
      "pk":39,
      "model":"products.product",
      "fields":{
         "title":"Girls Coats & Jackets",
         "description":"Girls Designer Coats & Jackets",
         "image":"media/pk_4.jpg",
         "price":39.99,
         "quantity":25,
         "detail":"classic something",
         "status":true,
         "create_at":"2020-10-25 10:42:07.596776",
         "update_at":"2020-11-25 17:03:03.625972",
         "category_id":4,
         "variant":"None",
         "has_variant":false,
         "new_edition":true,
         "discount_30_percent":false,
         "rate":4.6
      }
   },
   {
      "pk":40,
      "model":"products.product",
      "fields":{
         "title":"Girls Coats & Jackets",
         "description":"Girls Designer Coats & Jackets",
         "image":"media/pk_5.jpg",
         "price":43.99,
         "quantity":25,
         "detail":"classic something",
         "status":true,
         "create_at":"2020-10-25 10:42:07.596776",
         "update_at":"2020-11-25 17:03:03.625972",
         "category_id":4,
         "variant":"None",
         "has_variant":false,
         "new_edition":true,
         "discount_30_percent":false,
         "rate":4.6
      }
   },
   {
      "pk":41,
      "model":"products.product",
      "fields":{
         "title":"Girls Tops",
         "description":"Designer Girls Tops",
         "image":"media/pk_6.jpg",
         "price":53.99,
         "quantity":25,
         "detail":"classic something",
         "status":true,
         "create_at":"2020-10-25 10:42:07.596776",
         "update_at":"2020-11-25 17:03:03.625972",
         "category_id":5,
         "variant":"None",
         "has_variant":false,
         "new_edition":true,
         "discount_30_percent":false,
         "rate":4.6
      }
   },
   {
      "pk":42,
      "model":"products.product",
      "fields":{
         "title":"Girls Tops",
         "description":"Designer Girls Tops",
         "image":"media/pk_7.jpg",
         "price":32.99,
         "quantity":25,
         "detail":"classic something",
         "status":true,
         "create_at":"2020-10-25 10:42:07.596776",
         "update_at":"2020-11-25 17:03:03.625972",
         "category_id":5,
         "variant":"None",
         "has_variant":false,
         "new_edition":true,
         "discount_30_percent":false,
         "rate":4.6
      }
   },
   {
      "pk":43,
      "model":"products.product",
      "fields":{
         "title":"Girls Tops",
         "description":"Designer Girls Tops",
         "image":"media/pk_8.jpg",
         "price":33.99,
         "quantity":25,
         "detail":"classic something",
         "status":true,
         "create_at":"2020-10-25 10:42:07.596776",
         "update_at":"2020-11-25 17:03:03.625972",
         "category_id":5,
         "variant":"None",
         "has_variant":false,
         "new_edition":true,
         "discount_30_percent":false,
         "rate":4.6
      }
   },
   {
      "pk":44,
      "model":"products.product",
      "fields":{
         "title":"Girls Tops",
         "description":"Designer Girls Tops",
         "image":"media/pk_9.jpg",
         "price":63.99,
         "quantity":25,
         "detail":"classic something",
         "status":true,
         "create_at":"2020-10-25 10:42:07.596776",
         "update_at":"2020-11-25 17:03:03.625972",
         "category_id":5,
         "variant":"None",
         "has_variant":false,
         "new_edition":true,
         "discount_30_percent":false,
         "rate":4.6
      }
   },
   {
      "pk":45,
      "model":"products.product",
      "fields":{
         "title":"Girls Tops",
         "description":"Designer Girls Tops",
         "image":"media/pk_10.jpg",
         "price":43.99,
         "quantity":25,
         "detail":"classic something",
         "status":true,
         "create_at":"2020-10-25 10:42:07.596776",
         "update_at":"2020-11-25 17:03:03.625972",
         "category_id":5,
         "variant":"None",
         "has_variant":false,
         "new_edition":true,
         "discount_30_percent":false,
         "rate":4.6
      }
   },
   {
      "pk":46,
      "model":"products.product",
      "fields":{
         "title":"Girls Damage Jeans",
         "description":"Stylish Damge Jeans",
         "image":"media/pk_1.jpg",
         "price":53.99,
         "quantity":25,
         "detail":"classic something",
         "status":true,
         "create_at":"2020-10-25 10:42:07.596776",
         "update_at":"2020-11-25 17:03:03.625972",
         "category_id":6,
         "variant":"None",
         "has_variant":false,
         "new_edition":true,
         "discount_30_percent":false,
         "rate":4.6
      }
   },
   {
      "pk":47,
      "model":"products.product",
      "fields":{
         "title":"Girls Damage Jeans",
         "description":"Stylish Damge Jeans",
         "image":"media/pk_2.jpg",
         "price":45.99,
         "quantity":25,
         "detail":"classic something",
         "status":true,
         "create_at":"2020-10-25 10:42:07.596776",
         "update_at":"2020-11-25 17:03:03.625972",
         "category_id":6,
         "variant":"None",
         "has_variant":false,
         "new_edition":false,
         "discount_30_percent":false,
         "rate":5
      }
   },
   {
      "pk":48,
      "model":"products.product",
      "fields":{
         "title":"Girls Damage Jeans",
         "description":"Stylish Damge Jeans",
         "image":"media/pk_3.jpg",
         "price":59.99,
         "quantity":25,
         "detail":"classic something",
         "status":true,
         "create_at":"2020-10-25 10:42:07.596776",
         "update_at":"2020-11-25 17:03:03.625972",
         "category_id":6,
         "variant":"None",
         "has_variant":false,
         "new_edition":true,
         "discount_30_percent":false,
         "rate":4.6
      }
   },
   {
      "pk":49,
      "model":"products.product",
      "fields":{
         "title":"Girls Damage Jeans",
         "description":"Stylish Damge Jeans",
         "image":"media/pk_4.jpg",
         "price":39.99,
         "quantity":25,
         "detail":"classic something",
         "status":true,
         "create_at":"2020-10-25 10:42:07.596776",
         "update_at":"2020-11-25 17:03:03.625972",
         "category_id":6,
         "variant":"None",
         "has_variant":false,
         "new_edition":true,
         "discount_30_percent":false,
         "rate":4.6
      }
   },
   {
      "pk":50,
      "model":"products.product",
      "fields":{
         "title":"Girls Damage Jeans",
         "description":"Stylish Damge Jeans",
         "image":"media/pk_5.jpg",
         "price":43.99,
         "quantity":25,
         "detail":"classic something",
         "status":true,
         "create_at":"2020-10-25 10:42:07.596776",
         "update_at":"2020-11-25 17:03:03.625972",
         "category_id":6,
         "variant":"None",
         "has_variant":false,
         "new_edition":true,
         "discount_30_percent":false,
         "rate":4.6
      }
   },
   {
      "pk":51,
      "model":"products.product",
      "fields":{
         "title":"Girls Jeans",
         "description":"Stylish Damge Jeans",
         "image":"media/pk_6.jpg",
         "price":53.99,
         "quantity":25,
         "detail":"classic something",
         "status":true,
         "create_at":"2020-10-25 10:42:07.596776",
         "update_at":"2020-11-25 17:03:03.625972",
         "category_id":7,
         "variant":"None",
         "has_variant":false,
         "new_edition":true,
         "discount_30_percent":false,
         "rate":4.6
      }
   },
   {
      "pk":52,
      "model":"products.product",
      "fields":{
         "title":"Girls Jeans",
         "description":"Stylish Jeans",
         "image":"media/pk_7.jpg",
         "price":32.99,
         "quantity":25,
         "detail":"classic something",
         "status":true,
         "create_at":"2020-10-25 10:42:07.596776",
         "update_at":"2020-11-25 17:03:03.625972",
         "category_id":7,
         "variant":"None",
         "has_variant":false,
         "new_edition":true,
         "discount_30_percent":false,
         "rate":4.6
      }
   },
   {
      "pk":53,
      "model":"products.product",
      "fields":{
         "title":"Girls Jeans",
         "description":"Stylish Jeans",
         "image":"media/pk_8.jpg",
         "price":33.99,
         "quantity":25,
         "detail":"classic something",
         "status":true,
         "create_at":"2020-10-25 10:42:07.596776",
         "update_at":"2020-11-25 17:03:03.625972",
         "category_id":7,
         "variant":"None",
         "has_variant":false,
         "new_edition":true,
         "discount_30_percent":false,
         "rate":4.6
      }
   },
   {
      "pk":54,
      "model":"products.product",
      "fields":{
         "title":"Girls Jeans",
         "description":"Stylish Jeans",
         "image":"media/pk_9.jpg",
         "price":63.99,
         "quantity":25,
         "detail":"classic something",
         "status":true,
         "create_at":"2020-10-25 10:42:07.596776",
         "update_at":"2020-11-25 17:03:03.625972",
         "category_id":7,
         "variant":"None",
         "has_variant":false,
         "new_edition":true,
         "discount_30_percent":false,
         "rate":4.6
      }
   },
   {
      "pk":55,
      "model":"products.product",
      "fields":{
         "title":"Girls Jeans",
         "description":"Stylish Jeans",
         "image":"media/pk_10.jpg",
         "price":43.99,
         "quantity":25,
         "detail":"classic something",
         "status":true,
         "create_at":"2020-10-25 10:42:07.596776",
         "update_at":"2020-11-25 17:03:03.625972",
         "category_id":7,
         "variant":"None",
         "has_variant":false,
         "new_edition":true,
         "discount_30_percent":false,
         "rate":4.6
      }
   }
]